polygon_protection/__init__.py
polygon_protection/polygon_protection.py
polygon_protection-0.0.1.dist-info/METADATA
polygon_protection-0.0.1.dist-info/WHEEL
polygon_protection-0.0.1.dist-info/top_level.txt
polygon_protection-0.0.1.dist-info/RECORD
