Metadata-Version: 2.1
Name: polygon-protection
Version: 0.0.1
Summary: A library to protect polygon access key information
Home-page: https://polygon_protection.readthedocs.io/
Author: Stefan Su
Author-email: ys5561@nyu.edu
License: MIT
Classifier: Intended Audience :: Developers
Classifier: License :: OSI Approved :: MIT License
Classifier: Programming Language :: Python
Classifier: Programming Language :: Python :: 3
Classifier: Programming Language :: Python :: 3.6
Classifier: Programming Language :: Python :: 3.7
Classifier: Programming Language :: Python :: 3.8
Classifier: Programming Language :: Python :: 3.9
Classifier: Operating System :: OS Independent
Requires-Dist: sqlalchemy
Requires-Dist: polygon-api-client
Requires-Dist: polygon
